{
    "keep": {
        "days": false,
        "amount": 1000
    },
    "auditLog": "log/.audit.json",
    "files": [
        {
            "date": 1531400664141,
            "name": "log/.log.2018-07-12",
            "hash": "68d0a4cb82f1a240626077883f2700eb"
        },
        {
            "date": 1531400669410,
            "name": "log/.log.2018-07-12",
            "hash": "4c494114e60eeeb6d55e1d09fa0a679e"
        },
        {
            "date": 1531400680426,
            "name": "log/log.2018-07-12",
            "hash": "0692886319a818123dbea22975de2c82"
        },
        {
            "date": 1531400741184,
            "name": "log/a.2018-07-12",
            "hash": "a02a2c5a9f6f750769e0b9ca46593fae"
        },
        {
            "date": 1531400762990,
            "name": "log/_.2018-07-12",
            "hash": "65a4beb4767ef213be839445043fe939"
        },
        {
            "date": 1531400791421,
            "name": "log/_.2018-07-12",
            "hash": "37afb4bf71a2ba6f4f2b0f0ac2807eab"
        },
        {
            "date": 1531400824523,
            "name": "log/_.2018-07-12",
            "hash": "63e912a248ed918dc2071689c9940997"
        },
        {
            "date": 1531400871596,
            "name": "log/_.2018-07-12",
            "hash": "e960cdf40f3dd6950cf70c9969e8098c"
        },
        {
            "date": 1531418177861,
            "name": "log/_.2018-07-13",
            "hash": "0e163cff654b1d5386dd3a0dfedbc7a1"
        },
        {
            "date": 1531418200231,
            "name": "log/_.2018-07-13",
            "hash": "3f28fa2a8045e5f207a2faf70a2ca6f4"
        },
        {
            "date": 1531418204234,
            "name": "log/_.2018-07-13",
            "hash": "058ab9a583a065d7a45f45cb50d4201f"
        },
        {
            "date": 1531418220928,
            "name": "log/_.2018-07-13",
            "hash": "5492fe115e0d914325d8c22c2c839fcc"
        },
        {
            "date": 1531418235160,
            "name": "log/_.2018-07-13",
            "hash": "72a46f677344957311bc4393a45f2ff4"
        },
        {
            "date": 1531418240814,
            "name": "log/_.2018-07-13",
            "hash": "082b232f9fe658920d0ecdaa1149405a"
        },
        {
            "date": 1531418245644,
            "name": "log/_.2018-07-13",
            "hash": "0c594cf9a1c46ca6878598beae9e5639"
        },
        {
            "date": 1531418396118,
            "name": "log/_.2018-07-13",
            "hash": "b7c17831432fe2013cdd37921cb593d4"
        },
        {
            "date": 1531418406482,
            "name": "log/_.2018-07-13",
            "hash": "af0d0d46bcd64c4646153b78b568a3bc"
        },
        {
            "date": 1531418414898,
            "name": "log/_.2018-07-13",
            "hash": "f1b30300a566257ffbf66a99514c4748"
        },
        {
            "date": 1531418425627,
            "name": "log/_.2018-07-13",
            "hash": "2d5f81ecc73e200ddbea8b0dfc862160"
        },
        {
            "date": 1531418508296,
            "name": "log/_.2018-07-13",
            "hash": "1d88f10cb0e7c85b87f2c7799e55e27e"
        },
        {
            "date": 1531418615716,
            "name": "log/_.2018-07-13",
            "hash": "5fe9787db3d9312be114a72480999c1f"
        },
        {
            "date": 1531418620142,
            "name": "log/_.2018-07-13",
            "hash": "4bb93c33f11edac00566ca794cec40c6"
        },
        {
            "date": 1531418734117,
            "name": "log/_.2018-07-13",
            "hash": "325d8b4420592cdb7e5dfcedc705b025"
        },
        {
            "date": 1531418775265,
            "name": "log/_.2018-07-13",
            "hash": "467e2234edc3708bbac87d16c062bb05"
        },
        {
            "date": 1531418780241,
            "name": "log/_.2018-07-13",
            "hash": "70ba52baf4abe07f3e097aac028e8304"
        },
        {
            "date": 1531418783493,
            "name": "log/_.2018-07-13",
            "hash": "1b2961f10f108b22bcfbb0284554e3e7"
        },
        {
            "date": 1531418812813,
            "name": "log/_.2018-07-13",
            "hash": "2307e00c6c4433748783aa338e7a8f08"
        },
        {
            "date": 1531418845871,
            "name": "log/_.2018-07-13",
            "hash": "6ac51acf03a960bb22ab898b5f3c5596"
        },
        {
            "date": 1531418862976,
            "name": "log/_.2018-07-13",
            "hash": "f712008aca176667c49c00f8c31f99ce"
        },
        {
            "date": 1531418902199,
            "name": "log/_.2018-07-13",
            "hash": "dd6f968d0c2d5682e81a9e4f507acc65"
        },
        {
            "date": 1531418983476,
            "name": "log/_.2018-07-13",
            "hash": "b91b0be81f2f2bd276edaad75edbeeec"
        },
        {
            "date": 1531419008660,
            "name": "log/_.2018-07-13",
            "hash": "756f6fb46dc7c02875ead94cde974efb"
        },
        {
            "date": 1531419020113,
            "name": "log/_.2018-07-13",
            "hash": "df20d37274b73640e461ab303ca4d278"
        },
        {
            "date": 1531419051290,
            "name": "log/_.2018-07-13",
            "hash": "e8f1b8107409fd994cff3767295b054c"
        },
        {
            "date": 1531419089017,
            "name": "log/_.2018-07-13",
            "hash": "41cc68997cb9ca176d99933ee71c7a60"
        },
        {
            "date": 1531419109729,
            "name": "log/_.2018-07-13",
            "hash": "38dd9f9fe2ba9396573d811ccfdb4e4a"
        },
        {
            "date": 1531419167053,
            "name": "log/_.2018-07-13",
            "hash": "16b5feea3a2451175096bbc2b5194908"
        },
        {
            "date": 1531419188524,
            "name": "log/_.2018-07-13",
            "hash": "e58444366421e56e640666726c7439ab"
        },
        {
            "date": 1531419203956,
            "name": "log/_.2018-07-13",
            "hash": "58578aa402a7916f8c926337caabb44d"
        },
        {
            "date": 1531419245642,
            "name": "log/_.2018-07-13",
            "hash": "258a2c4eb674663d7b7896a48111fd1b"
        },
        {
            "date": 1531419250595,
            "name": "log/_.2018-07-13",
            "hash": "577a95d1933421b4f44210fc48f40a36"
        },
        {
            "date": 1531419269170,
            "name": "log/_.2018-07-13",
            "hash": "28ecc1c6b88689d4740cc86fc93db1e4"
        },
        {
            "date": 1531419302311,
            "name": "log/_.2018-07-13",
            "hash": "fbfa42f2d67511fc34e26a6850f1f413"
        },
        {
            "date": 1531419358624,
            "name": "log/_.2018-07-13",
            "hash": "ec5f33926d00f6c143513b5ed3d49b1f"
        },
        {
            "date": 1531419381993,
            "name": "log/_.2018-07-13",
            "hash": "91caf03b168cc3d1240213b6118cdbf8"
        },
        {
            "date": 1531419442562,
            "name": "log/_.2018-07-13",
            "hash": "20eae3ed432591e80a03599b50a26c20"
        },
        {
            "date": 1531419456500,
            "name": "log/_.2018-07-13",
            "hash": "9df018de0d6f0e1c258db800256d9849"
        },
        {
            "date": 1531419467262,
            "name": "log/_.2018-07-13",
            "hash": "b4cbb8e2ca6edeb20684e453716eb8e3"
        },
        {
            "date": 1531419481274,
            "name": "log/_.2018-07-13",
            "hash": "81f56075a5afa2a2788f9486815cad24"
        },
        {
            "date": 1531419997090,
            "name": "log/_.2018-07-12",
            "hash": "6b1b44a207349c7868d16d9e9ec80afc"
        },
        {
            "date": 1531420279816,
            "name": "log/_.2018-07-12",
            "hash": "a748f629cebaee41babf71d7601cd6e9"
        },
        {
            "date": 1531420400146,
            "name": "log/_.2018-07-12",
            "hash": "3845091d164e6eac8b40f28967869f8b"
        },
        {
            "date": 1531420690107,
            "name": "log/_.2018-07-12",
            "hash": "68a8a2f77eefc2225e65ad8c17aedfec"
        },
        {
            "date": 1531420785421,
            "name": "log/_.2018-07-12",
            "hash": "a872e30d2994cf138c906763e285eb7b"
        },
        {
            "date": 1531420787373,
            "name": "log/_.2018-07-12",
            "hash": "e613fd03e72872b995cf8efd1242ccfc"
        },
        {
            "date": 1531420788890,
            "name": "log/_.2018-07-12",
            "hash": "8ac0b5d56b0d4d29838f89330f85aa8c"
        },
        {
            "date": 1531420790638,
            "name": "log/_.2018-07-12",
            "hash": "7dcdd4af045b3b099f2296fa50c14882"
        },
        {
            "date": 1531420792087,
            "name": "log/_.2018-07-12",
            "hash": "3152dbd9e88064aa00d061af3f52e7dc"
        },
        {
            "date": 1531420793839,
            "name": "log/_.2018-07-12",
            "hash": "19d9c25c7ce2bdeade4917f9b3d7b877"
        },
        {
            "date": 1531420872117,
            "name": "log/_.2018-07-12",
            "hash": "51f2544f9848ed1eccc81313cb1bff04"
        },
        {
            "date": 1531425283271,
            "name": "log/_.2018-07-12",
            "hash": "44e4f33e8b5822ff9e53e215d97ebbb9"
        },
        {
            "date": 1531425541808,
            "name": "log/_.2018-07-12",
            "hash": "0a08d15d1dba5506857f2c2ba85b2e4e"
        },
        {
            "date": 1531425555391,
            "name": "log/_.2018-07-12",
            "hash": "cbaefb76aec4fcb933f6d5d5e8ffe44b"
        },
        {
            "date": 1531425596473,
            "name": "log/_.2018-07-12",
            "hash": "aa4bfddac20f5999290e09c11ff8cfbc"
        },
        {
            "date": 1531425841335,
            "name": "log/_.2018-07-12",
            "hash": "f3a2ae212be6cf2b11b36b20f80fbb42"
        },
        {
            "date": 1531425928346,
            "name": "log/_.2018-07-12",
            "hash": "12f8e791851c79de107dae6ef61da2d0"
        },
        {
            "date": 1531450163463,
            "name": "log/_.2018-07-13",
            "hash": "083e23ee1c99b3b370313aa3d536c708"
        },
        {
            "date": 1531460472436,
            "name": "log/_.2018-07-13",
            "hash": "7a83e19de5d3542f9fee3ab52357f1c6"
        },
        {
            "date": 1531460622500,
            "name": "log/_.2018-07-13",
            "hash": "962097611177a98a1663141f0d2b7571"
        },
        {
            "date": 1531460787642,
            "name": "log/_.2018-07-13",
            "hash": "9100deb94cf099690695148d7fccc0a2"
        },
        {
            "date": 1531463769087,
            "name": "log/_.2018-07-13",
            "hash": "a61c663598e378222c6121887d5534b5"
        },
        {
            "date": 1531464588327,
            "name": "log/_.2018-07-13",
            "hash": "489ee9e6e3ae61fcb42acae7c38a0c17"
        },
        {
            "date": 1531467565515,
            "name": "log/_.2018-07-13",
            "hash": "aa3c4868b7f9e7e9954ee4924765ac01"
        },
        {
            "date": 1531467571114,
            "name": "log/_.2018-07-13",
            "hash": "e342d9fcd6517299f503b982a0e2adeb"
        },
        {
            "date": 1531468083717,
            "name": "log/_.2018-07-13",
            "hash": "149645928ca2a6db246926c017b7bf1b"
        },
        {
            "date": 1531468171038,
            "name": "log/_.2018-07-13",
            "hash": "bbd1429bc9604e07e7444c02745ac413"
        },
        {
            "date": 1531468236095,
            "name": "log/_.2018-07-13",
            "hash": "43959402b602386fc4fcc139db588429"
        },
        {
            "date": 1531468243541,
            "name": "log/_.2018-07-13",
            "hash": "65e0d2b1dda1ec11f8b0f31f2d41137b"
        },
        {
            "date": 1531468261094,
            "name": "log/_.2018-07-13",
            "hash": "744c7e5127ccac1c6b2794ec8b6a723c"
        },
        {
            "date": 1531468300380,
            "name": "log/_.2018-07-13",
            "hash": "13f3d54d833d4ff851ccf6947663adc3"
        },
        {
            "date": 1531468305358,
            "name": "log/_.2018-07-13",
            "hash": "02314342657cb590ecc5513399d8265a"
        },
        {
            "date": 1531468326287,
            "name": "log/_.2018-07-13",
            "hash": "f8a5be40a02f2f1f897e511af5275b6f"
        },
        {
            "date": 1531468377807,
            "name": "log/_.2018-07-13",
            "hash": "b4d237e1f135a1e6bec6f496045f7c17"
        },
        {
            "date": 1531468403761,
            "name": "log/_.2018-07-13",
            "hash": "52699010bb4f0e162e606eb4f40d09f1"
        },
        {
            "date": 1531468453843,
            "name": "log/_.2018-07-13",
            "hash": "fdc4b77b7c6eaf6b40a899eda9667cae"
        },
        {
            "date": 1531468478317,
            "name": "log/_.2018-07-13",
            "hash": "3434768f7adcb00735d24ca6526b177e"
        },
        {
            "date": 1531468486132,
            "name": "log/_.2018-07-13",
            "hash": "edc2093e830d8cb7aab08037c77de07a"
        },
        {
            "date": 1531472388320,
            "name": "log/_.2018-07-13",
            "hash": "07d269d9d554157882531309d121d7ee"
        },
        {
            "date": 1531472522229,
            "name": "log/_.2018-07-13",
            "hash": "cec391415bb3c133a3f60aea1c2ecd93"
        },
        {
            "date": 1531472849814,
            "name": "log/_.2018-07-13",
            "hash": "3e920b086099f82f6a43048b596611e4"
        },
        {
            "date": 1531472853211,
            "name": "log/_.2018-07-13",
            "hash": "2f78d5b019b3934f8e373a90ef10405b"
        },
        {
            "date": 1531472862445,
            "name": "log/_.2018-07-13",
            "hash": "13cbed86d8d1e0e02e5d7ff5eb2ffbed"
        },
        {
            "date": 1531473634406,
            "name": "log/_.2018-07-13",
            "hash": "45bdf2ff40d5faf4d566990b6e87b9a2"
        },
        {
            "date": 1531473649613,
            "name": "log/_.2018-07-13",
            "hash": "e5a8d98f376670ac2c40ab3c203ec2d7"
        },
        {
            "date": 1531473780871,
            "name": "log/_.2018-07-13",
            "hash": "704790b1970b00b8ff3ec0a98556465a"
        },
        {
            "date": 1531476037642,
            "name": "log/_.2018-07-13",
            "hash": "654acf004e30431ae27e4af0e64c04fd"
        },
        {
            "date": 1531476119375,
            "name": "log/_.2018-07-13",
            "hash": "c063330bfe75f6039e23a2182882b049"
        },
        {
            "date": 1531476219692,
            "name": "log/_.2018-07-13",
            "hash": "8d4f6245b03f4fd1d1163bc670bffed1"
        },
        {
            "date": 1531476255048,
            "name": "log/_.2018-07-13",
            "hash": "240ff5acebbf5fc017737f88a8f64318"
        },
        {
            "date": 1531476269412,
            "name": "log/_.2018-07-13",
            "hash": "cdde871db055fc5846a490571ee4ae91"
        },
        {
            "date": 1531476275163,
            "name": "log/_.2018-07-13",
            "hash": "4499db49c6f9f726722347b859ce079f"
        },
        {
            "date": 1531476319309,
            "name": "log/_.2018-07-13",
            "hash": "614579e181090cdc1df8347aa5ad2ff7"
        },
        {
            "date": 1531477950668,
            "name": "log/_.2018-07-13",
            "hash": "3be01e9b80d87716a7969f19b7a3d28a"
        },
        {
            "date": 1531478001512,
            "name": "log/_.2018-07-13",
            "hash": "3a10f3bf1f973ebab9324b4939498a6d"
        },
        {
            "date": 1531478021633,
            "name": "log/_.2018-07-13",
            "hash": "666fafd8aecf2d909487d39c7af99156"
        },
        {
            "date": 1531478038844,
            "name": "log/_.2018-07-13",
            "hash": "36b705eef5792faf19bac9b803476d5d"
        },
        {
            "date": 1531478658180,
            "name": "log/_.2018-07-13",
            "hash": "cc4ae8741dda5817e16bb59beeea1ba5"
        },
        {
            "date": 1531478663355,
            "name": "log/_.2018-07-13",
            "hash": "f2c22dd4ee187cdf0e37ed0e561f8851"
        },
        {
            "date": 1531478671825,
            "name": "log/_.2018-07-13",
            "hash": "94c8b61156834aba27b29a3bf7d608a8"
        },
        {
            "date": 1531478712270,
            "name": "log/_.2018-07-13",
            "hash": "a0db8626c7eedd636b6770060573a0d4"
        },
        {
            "date": 1531478715780,
            "name": "log/_.2018-07-13",
            "hash": "2fc3b51209e856662d7c3d9c5b6a3e64"
        },
        {
            "date": 1531478724896,
            "name": "log/_.2018-07-13",
            "hash": "feacf815cfd0e994feda99312556f9a1"
        },
        {
            "date": 1531478732591,
            "name": "log/_.2018-07-13",
            "hash": "181ffea6927996c9bce5e0308fa783d4"
        },
        {
            "date": 1531478746061,
            "name": "log/_.2018-07-13",
            "hash": "648622e0e65d2365bc8821617d27080c"
        },
        {
            "date": 1531478759058,
            "name": "log/_.2018-07-13",
            "hash": "6e14da161698d677cbc041276dcebf64"
        },
        {
            "date": 1531478767241,
            "name": "log/_.2018-07-13",
            "hash": "15389fd6b80be1991d8b2e292dcd84f6"
        },
        {
            "date": 1531478840394,
            "name": "log/_.2018-07-13",
            "hash": "68145230430d1b4d16fb0110895d8143"
        },
        {
            "date": 1531478876879,
            "name": "log/_.2018-07-13",
            "hash": "9a5d34938bd3d3e073c183aa41dffa8a"
        },
        {
            "date": 1531478916837,
            "name": "log/_.2018-07-13",
            "hash": "ac9f26a7a4d0bb2db7c99d6a92cba25a"
        },
        {
            "date": 1531478950338,
            "name": "log/_.2018-07-13",
            "hash": "6b7df0006c62785efd347e90eb1c699d"
        },
        {
            "date": 1531478973598,
            "name": "log/_.2018-07-13",
            "hash": "1e8ced5c91abff98b95e659ae2088822"
        },
        {
            "date": 1531478991822,
            "name": "log/_.2018-07-13",
            "hash": "d1d6a2b4d33127301d207d25c09c3852"
        },
        {
            "date": 1531478995596,
            "name": "log/_.2018-07-13",
            "hash": "08e848367b04d753d1d54ff1774e796f"
        },
        {
            "date": 1531478999006,
            "name": "log/_.2018-07-13",
            "hash": "132467661e1f02d45de7d54d2a0828c5"
        },
        {
            "date": 1531479006456,
            "name": "log/_.2018-07-13",
            "hash": "a6a22bad7da8ba8a76c6d3f9bd7c873e"
        },
        {
            "date": 1531479021082,
            "name": "log/_.2018-07-13",
            "hash": "4a6844911838af8b50254270306b255e"
        },
        {
            "date": 1531479131257,
            "name": "log/_.2018-07-13",
            "hash": "591a43acf52c98dee54a2f6ed81cf664"
        },
        {
            "date": 1531479192618,
            "name": "log/_.2018-07-13",
            "hash": "7f95f0d1eb3c52ef9ceb40105fc9d52b"
        },
        {
            "date": 1531479216159,
            "name": "log/_.2018-07-13",
            "hash": "60b1b24c29f3448d7a3483de485b8df6"
        },
        {
            "date": 1531479250585,
            "name": "log/_.2018-07-13",
            "hash": "c3e374d7e00aa8775aebf350cf03bd81"
        },
        {
            "date": 1531479300951,
            "name": "log/_.2018-07-13",
            "hash": "3e9c0b68bad44f26f5c53a6269e8fd1c"
        },
        {
            "date": 1531479358214,
            "name": "log/_.2018-07-13",
            "hash": "fa214e52ef95a9a2cdd8ad3a41d1bc84"
        },
        {
            "date": 1531479391397,
            "name": "log/_.2018-07-13",
            "hash": "7b78b35c322c4309ae1375acffd6f6f6"
        },
        {
            "date": 1531479396216,
            "name": "log/_.2018-07-13",
            "hash": "0807ebbe2326d52d7389a77b3e1cee9b"
        },
        {
            "date": 1531479462844,
            "name": "log/_.2018-07-13",
            "hash": "4097aded59289c6d9261d31db241fd3d"
        },
        {
            "date": 1531479495705,
            "name": "log/_.2018-07-13",
            "hash": "3a72628d6f7d1b529f5e61bd6254af1c"
        },
        {
            "date": 1531479518545,
            "name": "log/_.2018-07-13",
            "hash": "c5c9545d2994381532abd85d1ef1a7fc"
        },
        {
            "date": 1531479575428,
            "name": "log/_.2018-07-13",
            "hash": "624e4c144de23f50ab600f556f610b99"
        },
        {
            "date": 1531479638704,
            "name": "log/_.2018-07-13",
            "hash": "a67f5556fda9f736c8a991db9068cbe2"
        },
        {
            "date": 1531479644689,
            "name": "log/_.2018-07-13",
            "hash": "82b88b7967f8416bc940a54625405978"
        },
        {
            "date": 1531479649940,
            "name": "log/_.2018-07-13",
            "hash": "171022c0b97e756ab81c2e0ca16b4181"
        },
        {
            "date": 1531479704825,
            "name": "log/_.2018-07-13",
            "hash": "29bcc046a83935c32fd709f8c143cbe9"
        },
        {
            "date": 1531479729757,
            "name": "log/_.2018-07-13",
            "hash": "981090e953c84b24ba50cce90bef113a"
        },
        {
            "date": 1531479795413,
            "name": "log/_.2018-07-13",
            "hash": "6628b23e15ade644f9561fea4d6a95a0"
        },
        {
            "date": 1531479802272,
            "name": "log/_.2018-07-13",
            "hash": "f9b7f36d9d06b17a36596b4d49d95aa4"
        },
        {
            "date": 1531479825253,
            "name": "log/_.2018-07-13",
            "hash": "fb64640c4eabe6f36588fa89d052bf15"
        },
        {
            "date": 1531479882383,
            "name": "log/_.2018-07-13",
            "hash": "5c4eae605abb7f61afb33a7cc22c9311"
        },
        {
            "date": 1531479919369,
            "name": "log/_.2018-07-13",
            "hash": "73a23f6c70ac5495e3670052013e570a"
        },
        {
            "date": 1531479949546,
            "name": "log/_.2018-07-13",
            "hash": "e96075c8d41b96c71c27fd16296b4a02"
        },
        {
            "date": 1531479953759,
            "name": "log/_.2018-07-13",
            "hash": "b1d8a39f0725bc433ad0d93ae6b1ec44"
        }
    ]
}